odoo/addons/account_avatax_exemption_base/README.rst
odoo/addons/account_avatax_exemption_base/__init__.py
odoo/addons/account_avatax_exemption_base/__manifest__.py
odoo/addons/account_avatax_exemption_base/data/ir_sequence_data.xml
odoo/addons/account_avatax_exemption_base/i18n/account_avatax_exemption_base.pot
odoo/addons/account_avatax_exemption_base/i18n/it.po
odoo/addons/account_avatax_exemption_base/models/__init__.py
odoo/addons/account_avatax_exemption_base/models/exemption.py
odoo/addons/account_avatax_exemption_base/models/partner.py
odoo/addons/account_avatax_exemption_base/models/res_country_state.py
odoo/addons/account_avatax_exemption_base/readme/CONTRIBUTORS.md
odoo/addons/account_avatax_exemption_base/readme/DESCRIPTION.md
odoo/addons/account_avatax_exemption_base/readme/USAGE.md
odoo/addons/account_avatax_exemption_base/security/ir.model.access.csv
odoo/addons/account_avatax_exemption_base/static/description/avatax_icon.png
odoo/addons/account_avatax_exemption_base/static/description/icon.png
odoo/addons/account_avatax_exemption_base/static/description/index.html
odoo/addons/account_avatax_exemption_base/views/avalara_exemption_view.xml
odoo/addons/account_avatax_exemption_base/views/res_country_state_view.xml
odoo_addon_account_avatax_exemption_base-18.0.1.0.0.8.dist-info/METADATA
odoo_addon_account_avatax_exemption_base-18.0.1.0.0.8.dist-info/WHEEL
odoo_addon_account_avatax_exemption_base-18.0.1.0.0.8.dist-info/top_level.txt
odoo_addon_account_avatax_exemption_base-18.0.1.0.0.8.dist-info/RECORD
