Metadata-Version: 2.1
Name: odoo-addon-account_avatax_exemption_base
Version: 18.0.1.0.0.8
Requires-Python: >=3.10
Requires-Dist: odoo==18.0.*
Summary: This application allows you to add exemptions base to Avatax
Home-page: https://github.com/OCA/account-fiscal-rule
License: LGPL-3
Author: Sodexis, Odoo Community Association (OCA)
Author-email: support@odoo-community.org
Classifier: Programming Language :: Python
Classifier: Framework :: Odoo
Classifier: Framework :: Odoo :: 18.0
Classifier: License :: OSI Approved :: GNU Lesser General Public License v3 (LGPLv3)
